pylibraft/GIT_COMMIT
pylibraft/VERSION
pylibraft/__init__.py
pylibraft/_version.py
pylibraft/config.py
pylibraft/common/CMakeLists.txt
pylibraft/common/__init__.pxd
pylibraft/common/__init__.py
pylibraft/common/ai_wrapper.py
pylibraft/common/cai_wrapper.py
pylibraft/common/cuda.cpython-310-x86_64-linux-gnu.so
pylibraft/common/cuda.pxd
pylibraft/common/cuda.pyx
pylibraft/common/device_ndarray.py
pylibraft/common/handle.cpython-310-x86_64-linux-gnu.so
pylibraft/common/handle.pxd
pylibraft/common/handle.pyx
pylibraft/common/input_validation.py
pylibraft/common/interruptible.cpython-310-x86_64-linux-gnu.so
pylibraft/common/interruptible.pxd
pylibraft/common/interruptible.pyx
pylibraft/common/mdspan.cpython-310-x86_64-linux-gnu.so
pylibraft/common/mdspan.pxd
pylibraft/common/mdspan.pyx
pylibraft/common/optional.pxd
pylibraft/common/outputs.py
pylibraft/common/cpp/__init__.pxd
pylibraft/common/cpp/__init__.py
pylibraft/common/cpp/mdspan.pxd
pylibraft/common/cpp/optional.pxd
pylibraft/random/CMakeLists.txt
pylibraft/random/__init__.pxd
pylibraft/random/__init__.py
pylibraft/random/rmat_rectangular_generator.cpython-310-x86_64-linux-gnu.so
pylibraft/random/rmat_rectangular_generator.pyx
pylibraft/random/cpp/__init__.pxd
pylibraft/random/cpp/__init__.py
pylibraft/random/cpp/rng_state.pxd
pylibraft/sparse/CMakeLists.txt
pylibraft/sparse/__init__.py
pylibraft/sparse/linalg/CMakeLists.txt
pylibraft/sparse/linalg/__init__.pxd
pylibraft/sparse/linalg/__init__.py
pylibraft/sparse/linalg/lanczos.cpython-310-x86_64-linux-gnu.so
pylibraft/sparse/linalg/lanczos.pyx
pylibraft/sparse/linalg/cpp/__init__.pxd
pylibraft/sparse/linalg/cpp/__init__.py
pylibraft_cu12.libs/libgomp-855c301a.so.1.0.0
pylibraft_cu12-25.12.0.dist-info/METADATA
pylibraft_cu12-25.12.0.dist-info/WHEEL
pylibraft_cu12-25.12.0.dist-info/RECORD
pylibraft_cu12-25.12.0.dist-info/licenses/LICENSE
pylibraft_cu12-25.12.0.dist-info/sboms/auditwheel.cdx.json
