Metadata-Version: 2.1
Name: pylibraft-cu12
Version: 25.12.0
Summary: RAFT: Reusable Algorithms Functions and other Tools
Author: NVIDIA Corporation
License: Apache-2.0
Classifier: Intended Audience :: Developers
Classifier: Programming Language :: Python
Classifier: Programming Language :: Python :: 3.10
Classifier: Programming Language :: Python :: 3.11
Classifier: Programming Language :: Python :: 3.12
Classifier: Programming Language :: Python :: 3.13
Project-URL: Homepage, https://github.com/rapidsai/raft
Project-URL: Documentation, https://docs.rapids.ai/api/raft/stable/
Requires-Python: >=3.10
Requires-Dist: cuda-python<13.0a0,>=12.9.2
Requires-Dist: libraft-cu12==25.12.*
Requires-Dist: numpy<3.0a0,>=1.23
Requires-Dist: rmm-cu12==25.12.*
Provides-Extra: test
Requires-Dist: cupy-cuda12x>=13.6.0; extra == "test"
Requires-Dist: pytest-cov; extra == "test"
Requires-Dist: pytest<9.0.0a0; extra == "test"
Requires-Dist: scikit-learn; extra == "test"
Requires-Dist: scipy; extra == "test"
